codebank/__init__.py
codebank/dllab.py
codebank/iotlab.py
codebank/mllab.py
codebank/wtlab.py
codebank-0.3.3.dist-info/LICENSE
codebank-0.3.3.dist-info/METADATA
codebank-0.3.3.dist-info/WHEEL
codebank-0.3.3.dist-info/top_level.txt
codebank-0.3.3.dist-info/RECORD
