Metadata-Version: 2.1
Name: codebank
Version: 0.3.3
Summary: summa oru pip module
Home-page: https://github.com/PraneshPK2005/codebank
Author: PraneshPk 
Author-email: praneshvaradharaj@gmail.com
Classifier: Programming Language :: Python :: 3
Classifier: License :: OSI Approved :: MIT License
Classifier: Operating System :: OS Independent
Requires-Python: >=3.10
License-File: LICENSE
Requires-Dist: numpy
